<?xml version="1.0"?>
<metadata xml:lang="en"><Esri><CreaDate>20230112</CreaDate><CreaTime>15035200</CreaTime><ArcGISFormat>1.0</ArcGISFormat><SyncOnce>TRUE</SyncOnce><ModDate>20230118</ModDate><ModTime>11470100</ModTime><scaleRange><minScale>150000000</minScale><maxScale>5000</maxScale></scaleRange><ArcGISProfile>ItemDescription</ArcGISProfile></Esri><tool name="DirectionalBuffer" displayname="Polygon Directional Graphic Buffer" toolboxalias="SolarSpace(tm) Toolbox v1.3" xmlns=""><arcToolboxHelpPath>c:\program files\arcgis\pro\Resources\Help\gp</arcToolboxHelpPath><parameters><param name="polygonInput" displayname="Input polygon feature class" type="Required" direction="Input" datatype="Feature Layer" expression="polygonInput"><dialogReference>&lt;DIV STYLE="text-align:Left;"&gt;&lt;DIV&gt;&lt;DIV&gt;&lt;P STYLE="margin:0 0 8 0;"&gt;&lt;SPAN&gt;&lt;SPAN&gt;Input feature class polygon &lt;/SPAN&gt;&lt;/SPAN&gt;&lt;/P&gt;&lt;P&gt;&lt;SPAN /&gt;&lt;/P&gt;&lt;/DIV&gt;&lt;/DIV&gt;&lt;/DIV&gt;</dialogReference></param><param name="polygonType" displayname="Polygon shape" type="Required" direction="Input" datatype="String" expression="Rectangles | Irregular"><dialogReference>&lt;DIV STYLE="text-align:Left;"&gt;&lt;DIV&gt;&lt;DIV&gt;&lt;P STYLE="margin:0 0 8 0;"&gt;&lt;SPAN&gt;&lt;SPAN&gt;Describes the polygon as “Rectangles” or “Irregular”&lt;/SPAN&gt;&lt;/SPAN&gt;&lt;/P&gt;&lt;/DIV&gt;&lt;/DIV&gt;&lt;/DIV&gt;</dialogReference></param><param name="xyzUnit" displayname="Measurement units" type="Required" direction="Input" datatype="String" expression="Foot | Meter"><dialogReference>&lt;DIV STYLE="text-align:Left;"&gt;&lt;DIV&gt;&lt;DIV&gt;&lt;P STYLE="margin:0 0 8 0;"&gt;&lt;SPAN&gt;&lt;SPAN&gt;Identifies the horizontal units of the dimensions for the layout design inputs (Foot or Meter)&lt;/SPAN&gt;&lt;/SPAN&gt;&lt;/P&gt;&lt;P&gt;&lt;SPAN /&gt;&lt;/P&gt;&lt;/DIV&gt;&lt;/DIV&gt;&lt;/DIV&gt;</dialogReference></param><param name="xEast" displayname="Distance to buffer to the east" type="Required" direction="Input" datatype="Double" expression="xEast"><dialogReference>&lt;DIV STYLE="text-align:Left;"&gt;&lt;DIV&gt;&lt;DIV&gt;&lt;P STYLE="margin:0 0 8 0;"&gt;&lt;SPAN&gt;&lt;SPAN&gt;Distance in the measurement units to buffer the polygon eastward&lt;/SPAN&gt;&lt;/SPAN&gt;&lt;/P&gt;&lt;P&gt;&lt;SPAN /&gt;&lt;/P&gt;&lt;/DIV&gt;&lt;/DIV&gt;&lt;/DIV&gt;</dialogReference></param><param name="xWest" displayname="Distance to buffer to the west" type="Required" direction="Input" datatype="Double" expression="xWest"><dialogReference>&lt;DIV STYLE="text-align:Left;"&gt;&lt;DIV&gt;&lt;DIV&gt;&lt;P STYLE="margin:0 0 8 0;"&gt;&lt;SPAN&gt;&lt;SPAN&gt;Distance in the measurement units to buffer the polygon westward&lt;/SPAN&gt;&lt;/SPAN&gt;&lt;/P&gt;&lt;P&gt;&lt;SPAN /&gt;&lt;/P&gt;&lt;/DIV&gt;&lt;/DIV&gt;&lt;/DIV&gt;</dialogReference></param><param name="yNorth" displayname="Distance to buffer to the north" type="Required" direction="Input" datatype="Double" expression="yNorth"><dialogReference>&lt;DIV STYLE="text-align:Left;"&gt;&lt;DIV&gt;&lt;DIV&gt;&lt;P STYLE="margin:0 0 8 0;"&gt;&lt;SPAN&gt;&lt;SPAN&gt;Distance in the measurement units to buffer the polygon northward&lt;/SPAN&gt;&lt;/SPAN&gt;&lt;/P&gt;&lt;P&gt;&lt;SPAN /&gt;&lt;/P&gt;&lt;/DIV&gt;&lt;/DIV&gt;&lt;/DIV&gt;</dialogReference></param><param name="ySouth" displayname="Distance to buffer to the south" type="Required" direction="Input" datatype="Double" expression="ySouth"><dialogReference>&lt;DIV STYLE="text-align:Left;"&gt;&lt;DIV&gt;&lt;DIV&gt;&lt;P STYLE="margin:0 0 8 0;"&gt;&lt;SPAN&gt;&lt;SPAN&gt;Distance in the measurement units to buffer the polygon southward&lt;/SPAN&gt;&lt;/SPAN&gt;&lt;/P&gt;&lt;/DIV&gt;&lt;/DIV&gt;&lt;/DIV&gt;</dialogReference></param><param name="fnVar" displayname="Accuracy resolution" type="Required" direction="Input" datatype="Double" expression="fnVar"><dialogReference>&lt;DIV STYLE="text-align:Left;"&gt;&lt;DIV&gt;&lt;DIV&gt;&lt;P STYLE="margin:0 0 8 0;"&gt;&lt;SPAN&gt;&lt;SPAN&gt;A value &amp;gt; 0 and &amp;lt;= 2. &lt;/SPAN&gt;&lt;/SPAN&gt;&lt;SPAN&gt;&lt;SPAN&gt;Only applicable to the “Irregular”&lt;/SPAN&gt;&lt;/SPAN&gt;&lt;SPAN&gt;&lt;SPAN&gt; option. Lower values will be more accurate, but will consume more memory&lt;/SPAN&gt;&lt;/SPAN&gt;&lt;/P&gt;&lt;P&gt;&lt;SPAN /&gt;&lt;/P&gt;&lt;/DIV&gt;&lt;/DIV&gt;&lt;/DIV&gt;</dialogReference></param><param name="polygonOutput" displayname="Output feature class" type="Required" direction="Output" datatype="Feature Class" expression="polygonOutput"><dialogReference>&lt;DIV STYLE="text-align:Left;"&gt;&lt;DIV&gt;&lt;DIV&gt;&lt;P STYLE="margin:0 0 8 0;"&gt;&lt;SPAN&gt;&lt;SPAN&gt;The output feature class of the directionally-buffered polygon&lt;/SPAN&gt;&lt;/SPAN&gt;&lt;/P&gt;&lt;P&gt;&lt;SPAN /&gt;&lt;/P&gt;&lt;/DIV&gt;&lt;/DIV&gt;&lt;/DIV&gt;</dialogReference></param></parameters><summary>&lt;DIV STYLE="text-align:Left;"&gt;&lt;DIV&gt;&lt;DIV&gt;&lt;P STYLE="text-align:Justify;margin:0 0 8 0;"&gt;&lt;SPAN&gt;&lt;SPAN&gt;Creates buffers dynamically in the cardinal directions from input polygons. Buffers can be variable in each direction.&lt;/SPAN&gt;&lt;/SPAN&gt;&lt;/P&gt;&lt;UL STYLE="margin:0 0 0 0;padding:0 0 0 0;"&gt;&lt;LI&gt;&lt;P STYLE="text-align:Justify;margin:0 0 8 0;"&gt;&lt;SPAN&gt;&lt;SPAN&gt;This tool was designed for rectangular polygons (for example, tracker rows), but can handle irregularly-shaped polygons. &lt;/SPAN&gt;&lt;/SPAN&gt;&lt;/P&gt;&lt;/LI&gt;&lt;LI&gt;&lt;P STYLE="text-align:Justify;margin:0 0 8 0;"&gt;&lt;SPAN&gt;&lt;SPAN&gt;An input is an option to describe the input polygons as “Rectangles” or “Irregular”&lt;/SPAN&gt;&lt;/SPAN&gt;&lt;SPAN&gt;&lt;SPAN&gt;.  &lt;/SPAN&gt;&lt;/SPAN&gt;&lt;/P&gt;&lt;UL STYLE="margin:0 0 0 0;padding:0 0 0 0;"&gt;&lt;LI&gt;&lt;P STYLE="text-align:Justify;margin:0 0 8 0;"&gt;&lt;SPAN&gt;&lt;SPAN&gt;Do not use&lt;/SPAN&gt;&lt;/SPAN&gt;&lt;SPAN&gt;&lt;SPAN&gt; the “Irregular”&lt;/SPAN&gt;&lt;/SPAN&gt;&lt;SPAN&gt;&lt;SPAN&gt; option for rectangular polygons &lt;/SPAN&gt;&lt;/SPAN&gt;&lt;SPAN&gt;&lt;SPAN&gt;–&lt;/SPAN&gt;&lt;/SPAN&gt;&lt;SPAN&gt;&lt;SPAN&gt; the buffers may not be exactly correct.&lt;/SPAN&gt;&lt;/SPAN&gt;&lt;/P&gt;&lt;/LI&gt;&lt;LI&gt;&lt;P STYLE="text-align:Justify;margin:0 0 8 0;"&gt;&lt;SPAN&gt;&lt;SPAN&gt;The buffers for irregular polygons are based on an algorithm that estimates the offset from the boundaries based on each individual side and the relationship to the &lt;/SPAN&gt;&lt;/SPAN&gt;&lt;SPAN&gt;&lt;SPAN&gt;offsets.  The offset may not be exact.  The smaller the number in the “Accuracy resolution”&lt;/SPAN&gt;&lt;/SPAN&gt;&lt;SPAN&gt;&lt;SPAN&gt; variable for irregular, the more exact the offset will be. However, the smaller the number the longer the tool will take to run.  &lt;/SPAN&gt;&lt;/SPAN&gt;&lt;/P&gt;&lt;/LI&gt;&lt;LI&gt;&lt;P STYLE="text-align:Justify;margin:0 0 8 0;"&gt;&lt;SPAN&gt;&lt;SPAN&gt;It is not recommended to use the &lt;/SPAN&gt;&lt;/SPAN&gt;&lt;SPAN&gt;&lt;SPAN&gt;“Irregular”&lt;/SPAN&gt;&lt;/SPAN&gt;&lt;SPAN&gt;&lt;SPAN&gt; option on very large polygons, as it can cause ArcGIS and your computer to crash due to memory limitations.  &lt;/SPAN&gt;&lt;/SPAN&gt;&lt;/P&gt;&lt;/LI&gt;&lt;/UL&gt;&lt;/LI&gt;&lt;LI&gt;&lt;P STYLE="text-align:Justify;margin:0 0 8 0;"&gt;&lt;SPAN&gt;&lt;SPAN&gt;This tool does not support negative buffers. &lt;/SPAN&gt;&lt;/SPAN&gt;&lt;/P&gt;&lt;/LI&gt;&lt;/UL&gt;&lt;P STYLE="text-align:Justify;margin:0 0 8 0;"&gt;&lt;SPAN /&gt;&lt;SPAN /&gt;&lt;/P&gt;&lt;/DIV&gt;&lt;/DIV&gt;&lt;/DIV&gt;</summary></tool><dataIdInfo><idCitation><resTitle>Polygon Directional Graphic Buffer</resTitle></idCitation><idCredit>KiloNewton SolarSpace © 2023</idCredit><searchKeys><keyword>utilities</keyword><keyword>graphic buffer</keyword><keyword>directional</keyword><keyword>polygon</keyword></searchKeys><resConst><Consts><useLimit>&lt;DIV STYLE="text-align:Left;"&gt;&lt;P STYLE="margin:0 0 16 0;"&gt;&lt;SPAN&gt;IN NO EVENT SHALL KILONEWTON LLC BE LIABLE TO THE CUSTOMER OR ANY OTHER PARTY OR ANY OTHER PERSON OR ENTITY FOR ANY SPECIAL, CONSEQUENTIAL, INCIDENTAL, INDIRECT, EXEMPLARY, OR PUNITIVE DAMAGES, HOWEVER CAUSED, ARISING OUT OF OR IN CONNECTION WITH THE INSTALLATION, IMPLEMENTATION, OR USE OF THE SOFTWARE, REGARDLESS OF THE FORM OF ACTION, WHETHER FOR BREACH OF CONTRACT, BREACH OF WARRANTY, TORT, NEGLIGENCE, INFRINGEMENT, OR OTHERWISE (INCLUDING, WITHOUT LIMITATION, DAMAGES BASED ON LOSS OF PROFITS, DATA, FILES, USE, BUSINESS OPPORTUNITY, OR CLAIMS OF THIRD PARTIES), AND WHETHER OR NOT THE PARTY HAS BEEN ADVISED OF THE POSSIBILITY OF SUCH DAMAGES.  THIS LIMITATION SHALL APPLY NOTWITHSTANDING ANY FAILURE OF ESSENTIAL PURPOSE OF ANY LIMITED REMEDY PROVIDED IN THE SOLARSPACE™ TOOLBOX END USER LICENSE AGREEMENT. &lt;/SPAN&gt;&lt;/P&gt;&lt;P STYLE="margin:0 0 8 0;"&gt;&lt;SPAN&gt;THE SOFTWARE IS PROVIDED “AS IS.”  KILONEWTON LLC MAKES NO WARRANTY OR REPRESENTATION OF ANY KIND TO THE CUSTOMER OR ANY THIRD PARTY, EXPRESS, IMPLIED, OR STATUTORY, WITH RESPECT TO THE SOFTWARE, INCLUDING, WITHOUT LIMITATION, ANY IMPLIED WARRANTY OF MERCHANTABILITY, ACCURACY, SATISFACTORY QUALITY, FITNESS FOR A PARTICULAR PURPOSE, USABILITY, INTEGRATION, OR NON-INFRINGEMENT, AND ALL SUCH WARRANTIES ARE HEREBY EXCLUDED BY KILONEWTON LLC AND WAIVED BY THE CUSTOMER.&lt;/SPAN&gt;&lt;/P&gt;&lt;/DIV&gt;</useLimit></Consts></resConst></dataIdInfo><distInfo><distributor><distorFormat><formatName>ArcToolbox Tool</formatName></distorFormat></distributor></distInfo><mdHrLv><ScopeCd value="005"></ScopeCd></mdHrLv><mdDateSt Sync="TRUE">20230118</mdDateSt></metadata>
